setup.cfg
setup.py
seaborn/__init__.py
seaborn/local_data.py
seaborn_local_data.egg-info/PKG-INFO
seaborn_local_data.egg-info/SOURCES.txt
seaborn_local_data.egg-info/dependency_links.txt
seaborn_local_data.egg-info/entry_points.txt
seaborn_local_data.egg-info/top_level.txt
test/test_local_data.py