Metadata-Version: 1.1
Name: seaborn-local-data
Version: 0.0.1
Summary: SeabornLocalData allows for the easystorage and parsing of data stored inlocal files
Home-page: https://github.com/SeabornGames/LocalData
Author: Ben Christenson
Author-email: Python@BenChristenson.com
License: MIT License
Download-URL: https://github.com/SeabornGames/LocalData/tarball/download
Keywords: data
Platform: UNKNOWN
Classifier: Intended Audience :: Developers
Classifier: Natural Language :: English
Classifier: License :: Other/Proprietary License
Classifier: Operating System :: POSIX :: Linux
Classifier: Programming Language :: Python
Classifier: Programming Language :: Python :: 2.7
Classifier: Programming Language :: Python :: 3.6
